MANIFEST.in
README.rst
README.txt
requirements.txt
setup.py
AGFramework/__init__.py
AGFramework/func_plus.py
AGFramework/scheduler.py
AGFramework/setting.py
AGFramework/time_plus.py
AGFramework/tracker.py
AGFramework.egg-info/PKG-INFO
AGFramework.egg-info/SOURCES.txt
AGFramework.egg-info/dependency_links.txt
AGFramework.egg-info/requires.txt
AGFramework.egg-info/top_level.txt
AGFramework/agadmin/__init__.py
AGFramework/agadmin/models.py
AGFramework/agadmin/views.py
AGFramework/agadmin/static/ttlogo.png
AGFramework/agadmin/static/css/bootstrap.min.css
AGFramework/agadmin/static/css/font-awesome.css
AGFramework/agadmin/static/css/style-responsive.css
AGFramework/agadmin/static/css/style.css
AGFramework/agadmin/static/echart/echarts.js
AGFramework/agadmin/static/echart/chart/bar.js
AGFramework/agadmin/static/echart/chart/line.js
AGFramework/agadmin/static/fonts/FontAwesome.otf
AGFramework/agadmin/static/fonts/fontawesome-webfont.eot
AGFramework/agadmin/static/fonts/fontawesome-webfont.svg
AGFramework/agadmin/static/fonts/fontawesome-webfont.ttf
AGFramework/agadmin/static/fonts/fontawesome-webfont.woff
AGFramework/agadmin/static/fonts/fontawesome-webfont.woff2
AGFramework/agadmin/static/fonts/glyphicons-halflings-regular.woff
AGFramework/agadmin/static/fonts/glyphicons-halflings-regular.woff2
AGFramework/agadmin/static/images/bg.jpg
AGFramework/agadmin/static/images/close.png
AGFramework/agadmin/static/images/mail.png
AGFramework/agadmin/static/images/minimal.png
AGFramework/agadmin/static/images/nav-expand.png
AGFramework/agadmin/static/images/next.png
AGFramework/agadmin/static/images/pass.png
AGFramework/agadmin/static/images/prev.png
AGFramework/agadmin/static/images/search-icon.png
AGFramework/agadmin/static/js/bootstrap.js
AGFramework/agadmin/static/js/jquery.dcjqaccordion.2.7.js
AGFramework/agadmin/static/js/jquery.nicescroll.js
AGFramework/agadmin/static/js/jquery2.0.3.min.js
AGFramework/agadmin/static/js/scripts.js
AGFramework/agadmin/templete/agbase.html
AGFramework/agadmin/templete/agindex.html
AGFramework/agadmin/templete/aglogin.html
AGFramework/agadmin/templete/agsystem.html
